MANIFEST.in
setup.py
restfulie/__init__.py
restfulie/api.py
restfulie/auth.py
restfulie/cached.py
restfulie/client.py
restfulie/codes.py
restfulie/configuration.py
restfulie/converters.py
restfulie/credentials.py
restfulie/links.py
restfulie/parser.py
restfulie/patchers.py
restfulie/processor.py
restfulie/request.py
restfulie/resource.py
restfulie/response.py
restfulie/restfulie.py
restfulie/services.py
restfulie/resources/__init__.py
restfulie/resources/form.py
restfulie/resources/json.py
restfulie/resources/multipart.py
restfulie/resources/plain.py
restfulie/resources/xml.py
sleipnir_restfulie.egg-info/PKG-INFO
sleipnir_restfulie.egg-info/SOURCES.txt
sleipnir_restfulie.egg-info/dependency_links.txt
sleipnir_restfulie.egg-info/not-zip-safe
sleipnir_restfulie.egg-info/requires.txt
sleipnir_restfulie.egg-info/top_level.txt