Metadata-Version: 1.1
Name: sleipnir-restfulie
Version: 0.19
Summary: Write hypermedia aware resource based clients and servers
Home-page: http://restfulie.caelumobjects.com/
Author: Carlos Martín
Author-email: inean.es@gmail.com
License: Apache 2.0
Download-URL: https://github.com/inean/restfulie-py
Keywords: rest,async,tornado,http,hypermedia
Platform: UNKNOWN
Classifier: Development Status :: 4 - Beta
Classifier: Environment :: Web Environment
Classifier: Intended Audience :: Developers
Classifier: License :: OSI Approved :: Apache Software License
Classifier: Operating System :: MacOS :: MacOS X
Classifier: Operating System :: Microsoft :: Windows
Classifier: Operating System :: POSIX
Classifier: Programming Language :: Python
